gpt_memory/__init__.py
gpt_memory/db.py
gpt_memory/db_config.json
gpt_memory/gpt.py
gpt_memory/memory.py
tests/__init__.py
gpt_memory-0.0.10.dist-info/METADATA
gpt_memory-0.0.10.dist-info/WHEEL
gpt_memory-0.0.10.dist-info/top_level.txt
gpt_memory-0.0.10.dist-info/RECORD
