Metadata-Version: 2.1
Name: gpt_memory
Version: 0.0.10
Summary: A LLM memory management library
Home-page: https://github.com/git4sun/gpt_memory
Author: Yang Sun
Author-email: sun@raaslabs.com
Classifier: Programming Language :: Python :: 3
Classifier: License :: OSI Approved :: MIT License
Classifier: Operating System :: OS Independent
Requires-Python: >=3.8
Requires-Dist: sqlalchemy
